rsp/__init__.py
rsp/data.py
rsp/amdim/__init__.py
rsp/amdim/inference.py
rsp/amdim/model.py
rsp/amdim/prep.py
rsp/moco_r50/__init__.py
rsp/moco_r50/data.py
rsp/moco_r50/inference.py
rsp/moco_r50/resnet.py
d3m_remote_sensing_pretrained-1.0.dist-info/METADATA
d3m_remote_sensing_pretrained-1.0.dist-info/WHEEL
d3m_remote_sensing_pretrained-1.0.dist-info/top_level.txt
d3m_remote_sensing_pretrained-1.0.dist-info/RECORD
