Metadata-Version: 2.1
Name: d3m-remote-sensing-pretrained
Version: 1.0
Summary: Pretrained remote sensing models
Home-page: https://gitlab.com/datadrivendiscovery/contrib/remote_sensing_pretrained
Author: Ben Johnson
Author-email: ben@canfield.io
License: MIT
Keywords: remote sensing,pretrained,rs
Platform: UNKNOWN
